philipstv/__init__.py
philipstv/__main__.py
philipstv/_cli.py
philipstv/_data.py
philipstv/_utils.py
philipstv/_version.py
philipstv/api.py
philipstv/exceptions.py
philipstv/pairing.py
philipstv/py.typed
philipstv/remote.py
philipstv/tv.py
philipstv/types.py
philipstv/model/__init__.py
philipstv/model/ambilight.py
philipstv/model/applications.py
philipstv/model/audio.py
philipstv/model/base.py
philipstv/model/channels.py
philipstv/model/general.py
philipstv/model/input.py
philipstv/model/pairing.py
philipstv-3.0.2.dist-info/METADATA
philipstv-3.0.2.dist-info/WHEEL
philipstv-3.0.2.dist-info/entry_points.txt
philipstv-3.0.2.dist-info/licenses/LICENSE
philipstv-3.0.2.dist-info/RECORD
