Metadata-Version: 2.4
Name: philipstv
Version: 3.0.2
Summary: CLI and library to control Philips Android-powered TVs.
Project-URL: repository, https://github.com/bcyran/philipstv
Project-URL: documentation, https://philipstv.readthedocs.io
Maintainer-email: Bazyli Cyran <bazyli@cyran.dev>
License: MIT
License-File: LICENSE
Keywords: ambilight,api-wrapper,cli,philips,tv
Classifier: Development Status :: 5 - Production/Stable
Classifier: Environment :: Console
Classifier: Intended Audience :: Developers
Classifier: Intended Audience :: End Users/Desktop
Classifier: License :: OSI Approved :: MIT License
Classifier: Programming Language :: Python :: 3 :: Only
Classifier: Programming Language :: Python :: 3.10
Classifier: Programming Language :: Python :: 3.11
Classifier: Programming Language :: Python :: 3.12
Classifier: Programming Language :: Python :: 3.13
Classifier: Programming Language :: Python :: 3.14
Classifier: Typing :: Typed
Requires-Python: >=3.10
Requires-Dist: pydantic>=2.4.2
Requires-Dist: requests>=2.27.1
Provides-Extra: cli
Requires-Dist: appdirs>=1.4.4; extra == 'cli'
Requires-Dist: click>=8.2.0; extra == 'cli'
Provides-Extra: docs
Requires-Dist: enum-tools[sphinx]>=0.13.0; extra == 'docs'
Requires-Dist: furo>=2025.7.19; extra == 'docs'
Requires-Dist: sphinx<9,>=7.2.6; extra == 'docs'
